vaex/scopes.py
vaex/superstrings.cpython-312-darwin.so
vaex/geo.py
vaex/serialize.py
vaex/functions.py
vaex/logging.py
vaex/misc_cmdline.py
vaex/promise.py
vaex/expresso.py
vaex/superagg.cpython-312-darwin.so
vaex/vaexfast.cpython-312-darwin.so
vaex/execution.py
vaex/grids.py
vaex/tasks.py
vaex/config.py
vaex/version.py
vaex/encoding.py
vaex/benchmark.py
vaex/legacy.py
vaex/dataset_mmap.py
vaex/datatype_test.py
vaex/memory.py
vaex/_version.py
vaex/registry.py
vaex/samp.py
vaex/events.py
vaex/dataframe.py
vaex/minisettings.py
vaex/convert.py
vaex/asyncio.py
vaex/cpu.py
vaex/superutils.cpython-312-darwin.so
vaex/cache.py
vaex/__init__.py
vaex/dataset_utils.py
vaex/formatting.py
vaex/selections.py
vaex/export.py
vaex/join.py
vaex/docstrings.py
vaex/rolling.py
vaex/dataset.py
vaex/hash.py
vaex/shift.py
vaex/delayed.py
vaex/dataframe_protocol.py
vaex/utils.py
vaex/kld.py
vaex/stat.py
vaex/csv.py
vaex/parallelize.py
vaex/settings.py
vaex/datatype.py
vaex/metal.py
vaex/progress.py
vaex/array_types.py
vaex/agg.py
vaex/groupby.py
vaex/expression.py
vaex/json.py
vaex/dataset_misc.py
vaex/image.py
vaex/__main__.py
vaex/multiprocessing.py
vaex/strings.py
vaex/column.py
vaex/struct.py
vaex/schema.py
vaex/multithreading.py
vaex/itertools.py
vaex/meta.py
vaex/misc/ordereddict.py
vaex/misc/samp.py
vaex/misc/expressions.py
vaex/misc/__init__.py
vaex/misc/pandawrap.py
vaex/misc/progressbar.py
vaex/misc/parallelize.py
vaex/core/_version.py
vaex/core/__init__.py
vaex/test/misc.py
vaex/test/expresso.py
vaex/test/plot.py
vaex/test/ui.py
vaex/test/__init__.py
vaex/test/all.py
vaex/test/dataset.py
vaex/test/__main__.py
vaex/test/cmodule.py
vaex/test/files/gaia-small-votable.vot
vaex/test/files/gaia-small-colfits-basic.fits
vaex/test/files/gaia-small-fits-basic.fits
vaex/test/files/gaia-small-colfits-plus.fits
vaex/test/files/default_amuse_plummer.hdf5
vaex/test/files/gaia-small-fits-plus.fits
vaex_core-4.19.0.dist-info/RECORD
vaex_core-4.19.0.dist-info/WHEEL
vaex_core-4.19.0.dist-info/entry_points.txt
vaex_core-4.19.0.dist-info/top_level.txt
vaex_core-4.19.0.dist-info/METADATA
vaex_core-4.19.0.dist-info/licenses/LICENSE.txt
